urlscan/__init__.py
urlscan/__main__.py
urlscan/_version.py
urlscan/urlchoose.py
urlscan/urlscan.py
urlscan/assets/tlds-alpha-by-domain.txt
urlscan-1.0.8.data/data/share/doc/urlscan/LICENSE
urlscan-1.0.8.data/data/share/doc/urlscan/README.md
urlscan-1.0.8.data/data/share/man/man1/urlscan.1
urlscan-1.0.8.dist-info/METADATA
urlscan-1.0.8.dist-info/WHEEL
urlscan-1.0.8.dist-info/entry_points.txt
urlscan-1.0.8.dist-info/licenses/LICENSE
urlscan-1.0.8.dist-info/RECORD
