Metadata-Version: 2.4
Name: urlscan
Version: 1.0.8
Summary: View/select the URLs in an email message or file
Project-URL: Homepage, https://github.com/firecat53/urlscan
Author-email: Scott Hansen <tech@firecat53.net>
License-Expression: GPL-2.0-or-later
License-File: LICENSE
Keywords: email,mutt,tmux,urlscan,urlview
Classifier: Development Status :: 5 - Production/Stable
Classifier: Environment :: Console
Classifier: Environment :: Console :: Curses
Classifier: License :: OSI Approved :: GNU General Public License v2 (GPLv2)
Classifier: Operating System :: OS Independent
Classifier: Programming Language :: Python
Classifier: Programming Language :: Python :: 3.7
Classifier: Programming Language :: Python :: 3.8
Classifier: Programming Language :: Python :: 3.9
Classifier: Programming Language :: Python :: 3.10
Classifier: Programming Language :: Python :: 3.11
Classifier: Programming Language :: Python :: 3.12
Classifier: Programming Language :: Python :: 3.13
Classifier: Topic :: Utilities
Requires-Dist: urwid>=1.2.1
